clearing/__init__.py
clearing/clear.py
clearing-1.0.0.dist-info/LICENSE
clearing-1.0.0.dist-info/METADATA
clearing-1.0.0.dist-info/WHEEL
clearing-1.0.0.dist-info/top_level.txt
clearing-1.0.0.dist-info/zip-safe
clearing-1.0.0.dist-info/RECORD
